LICENSE
giant_social_links/__init__.py
giant_social_links/admin.py
giant_social_links/apps.py
giant_social_links/context_processors.py
giant_social_links/migrations/0001_initial.py
giant_social_links/migrations/__init__.py
giant_social_links/models.py
giant_social_links/test_context_processors.py
giant_social_links-0.1.1.dist-info/LICENSE
giant_social_links-0.1.1.dist-info/WHEEL
giant_social_links-0.1.1.dist-info/METADATA
giant_social_links-0.1.1.dist-info/RECORD
