Metadata-Version: 2.1
Name: giant-social-links
Version: 0.1.1
Summary: A small reuseable django app that allows social media links to be added via the admin.
Home-page: https://github.com/giantmade/giant-social-links
License: MIT
Keywords: giant_social_links,app
Author: Dominic Chaple
Author-email: domchaple@gmail.com
Requires-Python: >=3.9,<4.0
Classifier: Environment :: Console
Classifier: License :: OSI Approved :: MIT License
Classifier: Operating System :: OS Independent
Classifier: Programming Language :: Python :: 3
Classifier: Programming Language :: Python :: 3.10
Classifier: Programming Language :: Python :: 3.9
Classifier: Topic :: Software Development :: Documentation
Classifier: Topic :: Software Development :: Libraries :: Python Modules
Requires-Dist: giant-mixins
Requires-Dist: giant-plugins
Project-URL: Repository, https://github.com/giantmade/giant-social-links
